hackle/__init__.py
hackle/config.py
hackle/decision.py
hackle/exceptions.py
hackle/hackle.py
hackle/logger.py
hackle/model.py
hackle/remote_config.py
hackle/version.py
hackle/commons/__init__.py
hackle/commons/enums.py
hackle/internal/__init__.py
hackle/internal/hackle_core.py
hackle/internal/concurrent/__init__.py
hackle/internal/concurrent/atomic/__init__.py
hackle/internal/concurrent/atomic/atomic_float.py
hackle/internal/concurrent/atomic/atomic_integer.py
hackle/internal/concurrent/atomic/atomic_reference.py
hackle/internal/concurrent/schedule/__init__.py
hackle/internal/concurrent/schedule/scheduler.py
hackle/internal/concurrent/schedule/thread_scheduler.py
hackle/internal/evaluation/__init__.py
hackle/internal/evaluation/action/__init__.py
hackle/internal/evaluation/action/action_resolver.py
hackle/internal/evaluation/bucket/__init__.py
hackle/internal/evaluation/bucket/bucketer.py
hackle/internal/evaluation/container/__init__.py
hackle/internal/evaluation/container/container_resolver.py
hackle/internal/evaluation/evaluator/__init__.py
hackle/internal/evaluation/evaluator/delegating_evaluator.py
hackle/internal/evaluation/evaluator/evaluator.py
hackle/internal/evaluation/evaluator/experiment/__init__.py
hackle/internal/evaluation/evaluator/experiment/experiment_evaluation.py
hackle/internal/evaluation/evaluator/experiment/experiment_evaluator.py
hackle/internal/evaluation/evaluator/experiment/experiment_request.py
hackle/internal/evaluation/evaluator/remoteconfig/__init__.py
hackle/internal/evaluation/evaluator/remoteconfig/remote_config_evaluation.py
hackle/internal/evaluation/evaluator/remoteconfig/remote_config_evaluator.py
hackle/internal/evaluation/evaluator/remoteconfig/remote_config_request.py
hackle/internal/evaluation/flow/__init__.py
hackle/internal/evaluation/flow/evaluation_flow.py
hackle/internal/evaluation/flow/evaluation_flow_factory.py
hackle/internal/evaluation/flow/flow_evaluator.py
hackle/internal/evaluation/match/__init__.py
hackle_sdk-3.8.0.dist-info/licenses/LICENSE
hackle_sdk-3.8.0.dist-info/METADATA
hackle_sdk-3.8.0.dist-info/WHEEL
hackle_sdk-3.8.0.dist-info/top_level.txt
hackle_sdk-3.8.0.dist-info/RECORD
